.gitignore
.travis.yml
CHANGELOG.rst
LICENSE-MIT
MANIFEST.in
README.rst
requirements-dev.txt
requirements.txt
setup.cfg
setup.py
test.sh
api_pagination/__init__.py
api_pagination/__init__.pyc
api_pagination/api_pagination.pyc
api_pagination.egg-info/PKG-INFO
api_pagination.egg-info/SOURCES.txt
api_pagination.egg-info/dependency_links.txt
api_pagination.egg-info/pbr.json
api_pagination.egg-info/top_level.txt
api_pagination/test/__init__.py
api_pagination/test/__init__.pyc
api_pagination/test/test.py
api_pagination/test/test.pyc