Metadata-Version: 1.1
Name: api-pagination
Version: 1.0.0
Summary: Pagination calculator designed for APIs
Home-page: https://github.com/underdogio/api-pagination
Author: Todd Wolfson
Author-email: todd@twolfson.com
License: MIT
Download-URL: https://github.com/underdogio/api-pagination/archive/master.zip
Keywords: paginate,pagination,calc,calculate,calculator,api
Platform: UNKNOWN
Classifier: Development Status :: 3 - Alpha
Classifier: Intended Audience :: Developers
Classifier: License :: Public Domain
Classifier: Operating System :: OS Independent
Classifier: Programming Language :: Python
